se/__init__.py
se/easy_xml.py
se/epub.py
se/executables.py
se/executables_create_draft.py
se/formatting.py
se/images.py
se/kobo.py
se/mobi.py
se/se_epub.py
se/se_epub_build.py
se/se_epub_generate_toc.py
se/se_epub_lint.py
se/spelling.py
se/typography.py
se/completions/bash/se
se/completions/zsh/_se
se/data/mathmlcontent2presentation.xsl
se/data/navdoc2ncx.xsl
se/data/words
se/data/templates/LICENSE.md
se/data/templates/colophon.xhtml
se/data/templates/compatibility.css
se/data/templates/content.opf
se/data/templates/core.css
se/data/templates/cover.jpg
se/data/templates/cover.svg
se/data/templates/gitignore
se/data/templates/header.xhtml
se/data/templates/imprint.xhtml
se/data/templates/kindle.css
se/data/templates/local.css
se/data/templates/logo.svg
se/data/templates/mimetype
se/data/templates/onix.xml
se/data/templates/proofreading.css
se/data/templates/titlepage.svg
se/data/templates/titlepage.xhtml
se/data/templates/toc.xhtml
se/data/templates/uncopyright.xhtml
se/data/templates/META-INF/container.xml
se/vendor/__init__.py
se/vendor/kindleunpack/__init__.py
se/vendor/kindleunpack/compatibility_utils.py
se/vendor/kindleunpack/kindleunpack.py
se/vendor/kindleunpack/mobi_cover.py
se/vendor/kindleunpack/mobi_dict.py
se/vendor/kindleunpack/mobi_header.py
se/vendor/kindleunpack/mobi_html.py
se/vendor/kindleunpack/mobi_index.py
se/vendor/kindleunpack/mobi_k8proc.py
se/vendor/kindleunpack/mobi_k8resc.py
se/vendor/kindleunpack/mobi_nav.py
se/vendor/kindleunpack/mobi_ncx.py
se/vendor/kindleunpack/mobi_opf.py
se/vendor/kindleunpack/mobi_pagemap.py
se/vendor/kindleunpack/mobi_sectioner.py
se/vendor/kindleunpack/mobi_split.py
se/vendor/kindleunpack/mobi_uncompress.py
se/vendor/kindleunpack/mobi_utils.py
se/vendor/kindleunpack/mobiml2xhtml.py
se/vendor/kindleunpack/unipath.py
se/vendor/kindleunpack/unpack_structure.py
standardebooks-1.0.18.dist-info/LICENSE.md
standardebooks-1.0.18.dist-info/METADATA
standardebooks-1.0.18.dist-info/WHEEL
standardebooks-1.0.18.dist-info/entry_points.txt
standardebooks-1.0.18.dist-info/top_level.txt
standardebooks-1.0.18.dist-info/RECORD
