Metadata-Version: 2.1
Name: standardebooks
Version: 1.0.18
Summary: The toolset used to produce Standard Ebooks epub ebooks.
Home-page: https://standardebooks.org
Author: Standard Ebooks
License: UNKNOWN
Project-URL: Source, https://github.com/standardebooks/tools/
Keywords: ebooks epub
Platform: UNKNOWN
Classifier: Development Status :: 5 - Production/Stable
Classifier: Intended Audience :: Developers
Classifier: Topic :: Software Development :: Build Tools
Classifier: License :: OSI Approved :: GNU General Public License v3 or later (GPLv3+)
Classifier: Programming Language :: Python :: 3
Classifier: Programming Language :: Python :: 3.5
Requires-Python: >=3.5
Requires-Dist: beautifulsoup4 (==4.6.0)
Requires-Dist: cssselect (==1.0.1)
Requires-Dist: ftfy (==5.3.0)
Requires-Dist: gitpython (==2.1.5)
Requires-Dist: lxml (==4.2.3)
Requires-Dist: psutil (==5.5.0)
Requires-Dist: pyhyphen (==3.0.1)
Requires-Dist: python-magic (==0.4.13)
Requires-Dist: regex (==2017.7.26)
Requires-Dist: requests (>=2.20.0)
Requires-Dist: roman (==2.0.0)
Requires-Dist: smartypants (==2.0.0)
Requires-Dist: titlecase (==0.11.0)
Requires-Dist: termcolor (==1.1.0)
Requires-Dist: terminaltables (==3.1.0)
